jupytervideo/__init__.py
jupytervideo/main.py
jupytervideo-0.1.0.dist-info/LICENSE
jupytervideo-0.1.0.dist-info/METADATA
jupytervideo-0.1.0.dist-info/WHEEL
jupytervideo-0.1.0.dist-info/RECORD
